{
  "project_info": {
    "project_number": "519030340855",
    "project_id": "fire-base-8baad",
    "storage_bucket": "fire-base-8baad.appspot.com"
  },
  "client": [
    {
      "client_info": {
        "mobilesdk_app_id": "1:519030340855:android:5d109b28f36a243e23a7f2",
        "android_client_info": {
          "package_name": "com.example.buoi8_firebase"
        }
      },
      "oauth_client": [
        {
          "client_id": "519030340855-6ao3p1ckurfi6b2lj3v7bo8vp018k41t.apps.googleusercontent.com",
          "client_type": 3
        }
      ],
      "api_key": [
        {
          "current_key": "AIzaSyAwRlNWJbs1DxDjIPaSvZsf3XCDFSWsmRY"
        }
      ],
      "services": {
        "appinvite_service": {
          "other_platform_oauth_client": [
            {
              "client_id": "519030340855-6ao3p1ckurfi6b2lj3v7bo8vp018k41t.apps.googleusercontent.com",
              "client_type": 3
            }
          ]
        }
      }
    }
  ],
  "configuration_version": "1"
}